README.md
setup.py
hostblock/__init__.py
hostblock/__main__.py
hostblock.egg-info/PKG-INFO
hostblock.egg-info/SOURCES.txt
hostblock.egg-info/dependency_links.txt
hostblock.egg-info/entry_points.txt
hostblock.egg-info/top_level.txt